resrm/__init__.py
resrm/cli.py
resrm/core.py
resrm-0.4.1.dist-info/LICENCE
resrm-0.4.1.dist-info/METADATA
resrm-0.4.1.dist-info/WHEEL
resrm-0.4.1.dist-info/entry_points.txt
resrm-0.4.1.dist-info/RECORD
