Metadata-Version: 2.1
Name: resrm
Version: 0.4.1
Summary: drop-in replacement for rm with undo/restore built-in.
Home-page: https://git.sysmd.uk/guardutils/resrm
License: GPL-3.0-or-later
Author: Marco D'Aleo
Author-email: marco@marcodaleo.com
Requires-Python: >=3.10,<4.0
Classifier: License :: OSI Approved :: GNU General Public License v3 or later (GPLv3+)
Classifier: Programming Language :: Python :: 3
Classifier: Programming Language :: Python :: 3.10
Classifier: Programming Language :: Python :: 3.11
Classifier: Programming Language :: Python :: 3.12
Classifier: Programming Language :: Python :: 3.13
Requires-Dist: argcomplete (>=2)
Project-URL: Repository, https://git.sysmd.uk/guardutils/resrm
